himena_seaborn/__init__.py
himena_seaborn/_doc.py
himena_seaborn/_figure.py
himena_seaborn/plotting.py
himena_seaborn-0.1.0.dist-info/METADATA
himena_seaborn-0.1.0.dist-info/WHEEL
himena_seaborn-0.1.0.dist-info/entry_points.txt
himena_seaborn-0.1.0.dist-info/licenses/LICENSE
himena_seaborn-0.1.0.dist-info/RECORD
