Metadata-Version: 2.4
Name: himena-seaborn
Version: 0.1.0
Summary: Calling seaborn plotting functions in himena
Project-URL: Documentation, https://github.com/hanjinliu/himena-seaborn#readme
Project-URL: Issues, https://github.com/hanjinliu/himena-seaborn/issues
Project-URL: Source, https://github.com/hanjinliu/himena-seaborn
Author-email: hanjinliu <liuhanjin.sc@gmail.com>
License: BSD 3-Clause License
License-File: LICENSE
Classifier: Development Status :: 4 - Beta
Classifier: Programming Language :: Python
Classifier: Programming Language :: Python :: 3.10
Classifier: Programming Language :: Python :: 3.11
Classifier: Programming Language :: Python :: 3.12
Classifier: Programming Language :: Python :: 3.13
Classifier: Programming Language :: Python :: Implementation :: CPython
Classifier: Programming Language :: Python :: Implementation :: PyPy
Requires-Python: >=3.10
Requires-Dist: himena
Requires-Dist: matplotlib
Requires-Dist: seaborn
Provides-Extra: testing
Requires-Dist: himena[testing]; extra == 'testing'
Requires-Dist: pyqt6; extra == 'testing'
Requires-Dist: pytest; extra == 'testing'
Requires-Dist: pytest-cov; extra == 'testing'
